LICENSE
MANIFEST.in
README.md
setup.cfg
setup.py
tap_tiktok_ads/__init__.py
tap_tiktok_ads/client.py
tap_tiktok_ads/discover.py
tap_tiktok_ads/schemas.py
tap_tiktok_ads/streams.py
tap_tiktok_ads/sync.py
tap_tiktok_ads.egg-info/PKG-INFO
tap_tiktok_ads.egg-info/SOURCES.txt
tap_tiktok_ads.egg-info/dependency_links.txt
tap_tiktok_ads.egg-info/entry_points.txt
tap_tiktok_ads.egg-info/requires.txt
tap_tiktok_ads.egg-info/top_level.txt
tap_tiktok_ads/schemas/ad_insights.json
tap_tiktok_ads/schemas/ad_insights_by_age_and_gender.json
tap_tiktok_ads/schemas/ad_insights_by_country.json
tap_tiktok_ads/schemas/ad_insights_by_platform.json
tap_tiktok_ads/schemas/adgroups.json
tap_tiktok_ads/schemas/ads.json
tap_tiktok_ads/schemas/advertisers.json
tap_tiktok_ads/schemas/campaign_insights_by_province.json
tap_tiktok_ads/schemas/campaigns.json